chatterbot/__init__.py
chatterbot/__main__.py
chatterbot/adapters.py
chatterbot/chatterbot.py
chatterbot/comparisons.py
chatterbot/constants.py
chatterbot/conversation.py
chatterbot/corpus.py
chatterbot/exceptions.py
chatterbot/filters.py
chatterbot/languages.py
chatterbot/parsing.py
chatterbot/preprocessors.py
chatterbot/response_selection.py
chatterbot/search.py
chatterbot/tagging.py
chatterbot/trainers.py
chatterbot/utils.py
chatterbot/ext/__init__.py
chatterbot/ext/django_chatterbot/__init__.py
chatterbot/ext/django_chatterbot/abstract_models.py
chatterbot/ext/django_chatterbot/admin.py
chatterbot/ext/django_chatterbot/apps.py
chatterbot/ext/django_chatterbot/model_admin.py
chatterbot/ext/django_chatterbot/models.py
chatterbot/ext/django_chatterbot/settings.py
chatterbot/ext/django_chatterbot/migrations/0001_initial.py
chatterbot/ext/django_chatterbot/migrations/0002_statement_extra_data.py
chatterbot/ext/django_chatterbot/migrations/0003_change_occurrence_default.py
chatterbot/ext/django_chatterbot/migrations/0004_rename_in_response_to.py
chatterbot/ext/django_chatterbot/migrations/0005_statement_created_at.py
chatterbot/ext/django_chatterbot/migrations/0006_create_conversation.py
chatterbot/ext/django_chatterbot/migrations/0007_response_created_at.py
chatterbot/ext/django_chatterbot/migrations/0008_update_conversations.py
chatterbot/ext/django_chatterbot/migrations/0009_tags.py
chatterbot/ext/django_chatterbot/migrations/0010_statement_text.py
chatterbot/ext/django_chatterbot/migrations/0011_blank_extra_data.py
chatterbot/ext/django_chatterbot/migrations/0012_statement_created_at.py
chatterbot/ext/django_chatterbot/migrations/0013_change_conversations.py
chatterbot/ext/django_chatterbot/migrations/0014_remove_statement_extra_data.py
chatterbot/ext/django_chatterbot/migrations/0015_statement_persona.py
chatterbot/ext/django_chatterbot/migrations/0016_statement_stemmed_text.py
chatterbot/ext/django_chatterbot/migrations/0017_tags_unique.py
ChatterBot2-1.1.0a7.dist-info/LICENSE
ChatterBot2-1.1.0a7.dist-info/METADATA
ChatterBot2-1.1.0a7.dist-info/WHEEL
ChatterBot2-1.1.0a7.dist-info/top_level.txt
ChatterBot2-1.1.0a7.dist-info/zip-safe
ChatterBot2-1.1.0a7.dist-info/RECORD
