Metadata-Version: 2.1
Name: ChatterBot2
Version: 1.1.0a7
Summary: ChatterBot is a machine learning, conversational dialog engine.
Home-page: https://github.com/gunthercox/ChatterBot
Author: Gunther Cox
Author-email: gunthercx@gmail.com
License: BSD
Download-URL: https://github.com/gunthercox/ChatterBot/tarball/1.1.0a7
Project-URL: Documentation, https://chatterbot.readthedocs.io
Keywords: ChatterBot,chatbot,chat,bot
Platform: any
Classifier: Development Status :: 4 - Beta
Classifier: Intended Audience :: Developers
Classifier: License :: OSI Approved :: BSD License
Classifier: Environment :: Console
Classifier: Environment :: Web Environment
Classifier: Operating System :: OS Independent
Classifier: Topic :: Software Development :: Libraries :: Python Modules
Classifier: Topic :: Communications :: Chat
Classifier: Topic :: Internet
Classifier: Programming Language :: Python
Classifier: Programming Language :: Python :: 3
Classifier: Programming Language :: Python :: 3.4
Classifier: Programming Language :: Python :: 3.5
Classifier: Programming Language :: Python :: 3.6
Classifier: Programming Language :: Python :: 3.7
Classifier: Programming Language :: Python :: 3.8
Classifier: Programming Language :: Python :: 3 :: Only
Requires-Python: >=3.4
License-File: LICENSE
